{
  "info": {
    "_postman_id": "4161dece-8c9e-4e4f-b673-db21de3e78a2",
    "name": "Insider Football Simulation API",
    "description": "Reviewer-friendly collection for the Insider Football Simulation API. Set base_url to http://localhost:8080 for local review or to the deployed Render URL.",
    "schema": "https://schema.getpostman.com/json/collection/v2.1.0/collection.json"
  },
  "variable": [
    {
      "key": "base_url",
      "value": "http://localhost:8080",
      "type": "string"
    },
    {
      "key": "match_id",
      "value": "1",
      "type": "string"
    },
    {
      "key": "team_id",
      "value": "1",
      "type": "string"
    }
  ],
  "item": [
    {
      "name": "Happy Path Demo",
      "item": [
        {
          "name": "Reset League",
          "request": {
            "method": "POST",
            "header": [],
            "url": "{{base_url}}/api/v1/league/reset"
          },
          "response": []
        },
        {
          "name": "Get Case Overview",
          "request": {
            "method": "GET",
            "header": [],
            "url": "{{base_url}}/api/v1/league/overview"
          },
          "response": []
        },
        {
          "name": "Get Standings",
          "request": {
            "method": "GET",
            "header": [],
            "url": "{{base_url}}/api/v1/league/table"
          },
          "response": []
        },
        {
          "name": "Play Next Week",
          "request": {
            "method": "POST",
            "header": [],
            "url": "{{base_url}}/api/v1/league/next-week"
          },
          "response": []
        },
        {
          "name": "Play All Remaining Weeks",
          "request": {
            "method": "POST",
            "header": [],
            "url": "{{base_url}}/api/v1/league/play-all"
          },
          "response": []
        },
        {
          "name": "Oracle Predictions",
          "request": {
            "method": "GET",
            "header": [],
            "url": "{{base_url}}/api/v1/simulation/oracle"
          },
          "response": []
        },
        {
          "name": "Get Match Details",
          "request": {
            "method": "GET",
            "header": [],
            "url": "{{base_url}}/api/v1/matches/{{match_id}}"
          },
          "response": []
        },
        {
          "name": "Edit Match Result",
          "request": {
            "method": "PUT",
            "header": [
              {
                "key": "Content-Type",
                "value": "application/json",
                "type": "text"
              }
            ],
            "body": {
              "mode": "raw",
              "raw": "{\n  \"home_score\": 3,\n  \"away_score\": 0\n}",
              "options": {
                "raw": {
                  "language": "json"
                }
              }
            },
            "url": "{{base_url}}/api/v1/matches/{{match_id}}"
          },
          "response": []
        },
        {
          "name": "Rollback To Week 2",
          "request": {
            "method": "POST",
            "header": [],
            "url": "{{base_url}}/api/v1/league/rollback/2"
          },
          "response": []
        },
        {
          "name": "Get Team Metrics",
          "request": {
            "method": "GET",
            "header": [],
            "url": "{{base_url}}/api/v1/teams/{{team_id}}/metrics"
          },
          "response": []
        },
        {
          "name": "Swagger UI",
          "request": {
            "method": "GET",
            "header": [],
            "url": "{{base_url}}/swagger/index.html"
          },
          "response": []
        }
      ]
    },
    {
      "name": "Validation And Error Cases",
      "item": [
        {
          "name": "Oracle Before Week 4",
          "request": {
            "method": "GET",
            "header": [],
            "url": "{{base_url}}/api/v1/simulation/oracle"
          },
          "response": []
        },
        {
          "name": "Edit Match Missing Away Score",
          "request": {
            "method": "PUT",
            "header": [
              {
                "key": "Content-Type",
                "value": "application/json",
                "type": "text"
              }
            ],
            "body": {
              "mode": "raw",
              "raw": "{\n  \"home_score\": 2\n}",
              "options": {
                "raw": {
                  "language": "json"
                }
              }
            },
            "url": "{{base_url}}/api/v1/matches/{{match_id}}"
          },
          "response": []
        },
        {
          "name": "Edit Match Unknown Field",
          "request": {
            "method": "PUT",
            "header": [
              {
                "key": "Content-Type",
                "value": "application/json",
                "type": "text"
              }
            ],
            "body": {
              "mode": "raw",
              "raw": "{\n  \"home_score\": 2,\n  \"away_score\": 1,\n  \"bonus_goal\": 1\n}",
              "options": {
                "raw": {
                  "language": "json"
                }
              }
            },
            "url": "{{base_url}}/api/v1/matches/{{match_id}}"
          },
          "response": []
        },
        {
          "name": "Edit Match Negative Score",
          "request": {
            "method": "PUT",
            "header": [
              {
                "key": "Content-Type",
                "value": "application/json",
                "type": "text"
              }
            ],
            "body": {
              "mode": "raw",
              "raw": "{\n  \"home_score\": -1,\n  \"away_score\": 1\n}",
              "options": {
                "raw": {
                  "language": "json"
                }
              }
            },
            "url": "{{base_url}}/api/v1/matches/{{match_id}}"
          },
          "response": []
        },
        {
          "name": "Rollback Out Of Range",
          "request": {
            "method": "POST",
            "header": [],
            "url": "{{base_url}}/api/v1/league/rollback/7"
          },
          "response": []
        },
        {
          "name": "Missing Match",
          "request": {
            "method": "GET",
            "header": [],
            "url": "{{base_url}}/api/v1/matches/999"
          },
          "response": []
        }
      ]
    }
  ]
}
